cloths_segmentation/__init__.py
cloths_segmentation/dataloaders.py
cloths_segmentation/inference.py
cloths_segmentation/metrics.py
cloths_segmentation/pre_trained_models.py
cloths_segmentation/train.py
cloths_segmentation/utils.py
cloths_segmentation-0.0.2.dist-info/LICENSE
cloths_segmentation-0.0.2.dist-info/METADATA
cloths_segmentation-0.0.2.dist-info/WHEEL
cloths_segmentation-0.0.2.dist-info/top_level.txt
cloths_segmentation-0.0.2.dist-info/RECORD
