Metadata-Version: 2.1
Name: cloths-segmentation
Version: 0.0.2
Summary: High quality model for cloths segmentation.
Home-page: https://github.com/ternaus/cloths_segmentation
Author: Vladimir Iglovikov
License: MIT
Platform: UNKNOWN
Classifier: License :: OSI Approved :: MIT License
Classifier: Intended Audience :: Developers
Classifier: Intended Audience :: Science/Research
Classifier: Operating System :: OS Independent
Classifier: Programming Language :: Python
Classifier: Programming Language :: Python :: 3
Classifier: Topic :: Software Development :: Libraries
Classifier: Topic :: Software Development :: Libraries :: Python Modules
Requires-Dist: albumentations
Requires-Dist: iglovikov-helper-functions
Requires-Dist: pytorch-lightning
Requires-Dist: pytorch-toolbelt
Requires-Dist: segmentation-models-pytorch
Requires-Dist: torch
Requires-Dist: tqdm
Requires-Dist: wandb
Provides-Extra: test
Requires-Dist: pytest ; extra == 'test'
